pubimport/__init__.py
pubimport-0.3.0.dist-info/entry_points.txt
pubimport-0.3.0.dist-info/WHEEL
pubimport-0.3.0.dist-info/METADATA
pubimport-0.3.0.dist-info/RECORD
