Metadata-Version: 2.1
Name: pubimport
Version: 0.3.0
Summary: 
Home-page: UNKNOWN
License: UNKNOWN
Author: Dominic Looser
Author-email: dominic.looser@gmail.com
Requires-Python: >=3.4,<4.0
Classifier: Programming Language :: Python :: 3
Classifier: Programming Language :: Python :: 3.4
Classifier: Programming Language :: Python :: 3.5
Classifier: Programming Language :: Python :: 3.6
Classifier: Programming Language :: Python :: 3.7
Requires-Dist: bibtexparser (>=1.1,<2.0)
Requires-Dist: click (>=7.0,<8.0)
Requires-Dist: dominate (>=2.3,<3.0)
